minemizer/__init__.py
minemizer/config.py
minemizer/core.py
minemizer-0.1.0.dist-info/METADATA
minemizer-0.1.0.dist-info/WHEEL
minemizer-0.1.0.dist-info/licenses/LICENSE
minemizer-0.1.0.dist-info/RECORD
