Metadata-Version: 2.4
Name: minemizer
Version: 0.1.0
Summary: Minemize your stuff
Project-URL: Homepage, https://github.com/ashirviskas/minemizer
Project-URL: Repository, https://github.com/ashirviskas/minemizer
Author-email: Matas Minelga <minematas@gmail.com>
License-Expression: MPL-2.0
License-File: LICENSE
Requires-Python: >=3.12
